hexahub/__init__.py
hexahub/cmd.py
hexahub/connection.py
hexahub/exceptions.py
hexahub/response.py
hexahub/utils.py
hexahub-1.0.9.dist-info/DESCRIPTION.rst
hexahub-1.0.9.dist-info/METADATA
hexahub-1.0.9.dist-info/RECORD
hexahub-1.0.9.dist-info/WHEEL
hexahub-1.0.9.dist-info/entry_points.txt
hexahub-1.0.9.dist-info/metadata.json
hexahub-1.0.9.dist-info/top_level.txt
hexahub-1.0.9.dist-info/zip-safe
