Metadata-Version: 2.0
Name: hexahub
Version: 1.0.9
Summary: Low level Python and CLI interface to GitHub
Home-page: https://github.com/Xobb/hexahub
Author: Alon Swartz
Author-email: alon@turnkeylinux.org
License: UNKNOWN
Platform: UNKNOWN
Requires-Dist: requests (==2.7)
Requires-Dist: simplejson
